botCreate/__init__.py
tests/__init__.py
tests/test_botCreate.py
botCreate-1.0.0.dist-info/METADATA
botCreate-1.0.0.dist-info/WHEEL
botCreate-1.0.0.dist-info/top_level.txt
botCreate-1.0.0.dist-info/RECORD
