Metadata-Version: 2.1
Name: botCreate
Version: 1.0.0
Summary: Create discord bots in python in only 10 seconds.
Home-page: https://github.com/ArticOff/botCreate
Author: Artic#3065
Author-email: artic.admisoffi@gmail.com
License: MIT
Platform: UNKNOWN
Classifier: Development Status :: 5 - Production/Stable
Classifier: License :: OSI Approved :: MIT License
Classifier: Intended Audience :: Developers
Classifier: Natural Language :: English
Requires-Dist: discord (==1.7.3)
